LICENSE
MANIFEST.in
Makefile
README.md
pyproject.toml
requirements_dev.txt
setup.py
tests/__init__.py
tests/test_user_agent.py
tests/test_warning.py
user_agent/__init__.py
user_agent/base.py
user_agent/cli.py
user_agent/device.py
user_agent/error.py
user_agent/py.typed
user_agent/warning.py
user_agent.egg-info/PKG-INFO
user_agent.egg-info/SOURCES.txt
user_agent.egg-info/dependency_links.txt
user_agent.egg-info/entry_points.txt
user_agent.egg-info/requires.txt
user_agent.egg-info/top_level.txt
user_agent/data/smartphone_dev_ext.json
user_agent/data/smartphone_dev_id.json
user_agent/data/tablet_dev_ext.json
user_agent/data/tablet_dev_id.json